Metadata-Version: 1.0
Name: accordion-project
Version: 0.0.6
Summary: ACCORDION Utils library
Home-page: UNKNOWN
Author: Konstantinos Tserpes
Author-email: tserpes@hua.gr
License: Apache-2.0
Platform: UNKNOWN
